{
    "key": "group_5c3c045f891cb",
    "title": "[Menu] Custom Menus",
    "fields": [
        {
            "key": "field_5c3c02997316a",
            "label": "Column Heading",
            "name": "column_heading",
            "type": "text",
            "instructions": "",
            "required": 0,
            "conditional_logic": 0,
            "wrapper": {
                "width": "50",
                "class": "",
                "id": ""
            },
            "default_value": "",
            "placeholder": "",
            "prepend": "",
            "append": "",
            "maxlength": ""
        },
        {
            "key": "field_5dde8afa0d0e0",
            "label": "Column Heading URL",
            "name": "column_heading_link",
            "type": "page_link",
            "instructions": "",
            "required": 0,
            "conditional_logic": [
                [
                    {
                        "field": "field_5e2723c7bde87",
                        "operator": "!=",
                        "value": "1"
                    }
                ]
            ],
            "wrapper": {
                "width": "50",
                "class": "",
                "id": ""
            },
            "post_type": [
                "page",
                "product"
            ],
            "taxonomy": "",
            "allow_null": 1,
            "allow_archives": 0,
            "multiple": 0
        },
        {
            "key": "field_5e2723eabde88",
            "label": "Column Heading Custom URL",
            "name": "ch_custom_url",
            "type": "url",
            "instructions": "",
            "required": 0,
            "conditional_logic": [
                [
                    {
                        "field": "field_5e2723c7bde87",
                        "operator": "==",
                        "value": "1"
                    }
                ]
            ],
            "wrapper": {
                "width": "50",
                "class": "",
                "id": ""
            },
            "default_value": "",
            "placeholder": ""
        },
        {
            "key": "field_5e2723c7bde87",
            "label": "Use Custom URL",
            "name": "use_custom_url",
            "type": "true_false",
            "instructions": "",
            "required": 0,
            "conditional_logic": 0,
            "wrapper": {
                "width": "",
                "class": "",
                "id": ""
            },
            "message": "",
            "default_value": 0,
            "ui": 1,
            "ui_on_text": "",
            "ui_off_text": ""
        },
        {
            "key": "field_5c3bd36e8e1ba",
            "label": "Sub Menu Builder",
            "name": "sub_menu_builder",
            "type": "repeater",
            "instructions": "",
            "required": 0,
            "conditional_logic": 0,
            "wrapper": {
                "width": "",
                "class": "",
                "id": ""
            },
            "collapsed": "",
            "min": 0,
            "max": 0,
            "layout": "block",
            "button_label": "Add Sub Menu Item",
            "sub_fields": [
                {
                    "key": "field_5c4544cbd9c82",
                    "label": "Content",
                    "name": "",
                    "type": "tab",
                    "instructions": "",
                    "required": 0,
                    "conditional_logic": 0,
                    "wrapper": {
                        "width": "",
                        "class": "",
                        "id": ""
                    },
                    "placement": "top",
                    "endpoint": 0
                },
                {
                    "key": "field_5c3c02ce7316c",
                    "label": "Link Text",
                    "name": "link_text",
                    "type": "text",
                    "instructions": "",
                    "required": 1,
                    "conditional_logic": 0,
                    "wrapper": {
                        "width": "50",
                        "class": "",
                        "id": ""
                    },
                    "default_value": "",
                    "placeholder": "",
                    "prepend": "",
                    "append": "",
                    "maxlength": ""
                },
                {
                    "key": "field_5c3c03267316f",
                    "label": "Page Link",
                    "name": "link",
                    "type": "page_link",
                    "instructions": "",
                    "required": 1,
                    "conditional_logic": [
                        [
                            {
                                "field": "field_5c3c02e17316d",
                                "operator": "!=",
                                "value": "1"
                            },
                            {
                                "field": "field_5dfb829429b69",
                                "operator": "!=",
                                "value": "1"
                            }
                        ]
                    ],
                    "wrapper": {
                        "width": "50",
                        "class": "",
                        "id": ""
                    },
                    "post_type": [
                        "page"
                    ],
                    "taxonomy": "",
                    "allow_null": 0,
                    "allow_archives": 0,
                    "multiple": 0
                },
                {
                    "key": "field_5dfb830129b6b",
                    "label": "Category Link",
                    "name": "category_link",
                    "type": "taxonomy",
                    "instructions": "",
                    "required": 1,
                    "conditional_logic": [
                        [
                            {
                                "field": "field_5dfb829429b69",
                                "operator": "==",
                                "value": "1"
                            },
                            {
                                "field": "field_5c3c02e17316d",
                                "operator": "!=",
                                "value": "1"
                            }
                        ]
                    ],
                    "wrapper": {
                        "width": "50",
                        "class": "",
                        "id": ""
                    },
                    "taxonomy": "product_cat",
                    "field_type": "select",
                    "allow_null": 0,
                    "add_term": 0,
                    "save_terms": 0,
                    "load_terms": 0,
                    "return_format": "id",
                    "multiple": 0
                },
                {
                    "key": "field_5c3c02fa7316e",
                    "label": "Custom Link",
                    "name": "custom_link",
                    "type": "url",
                    "instructions": "",
                    "required": 1,
                    "conditional_logic": [
                        [
                            {
                                "field": "field_5c3c02e17316d",
                                "operator": "==",
                                "value": "1"
                            }
                        ]
                    ],
                    "wrapper": {
                        "width": "50",
                        "class": "",
                        "id": ""
                    },
                    "default_value": "",
                    "placeholder": ""
                },
                {
                    "key": "field_5c4544d8d9c83",
                    "label": "Options",
                    "name": "",
                    "type": "tab",
                    "instructions": "",
                    "required": 0,
                    "conditional_logic": 0,
                    "wrapper": {
                        "width": "",
                        "class": "",
                        "id": ""
                    },
                    "placement": "top",
                    "endpoint": 0
                },
                {
                    "key": "field_5dfb829429b69",
                    "label": "Link Type",
                    "name": "link_type",
                    "type": "true_false",
                    "instructions": "Check to change the link type to category. The default is set to page. Will be overridden by Use Custom URL if that option is set.",
                    "required": 0,
                    "conditional_logic": 0,
                    "wrapper": {
                        "width": "50",
                        "class": "",
                        "id": ""
                    },
                    "message": "",
                    "default_value": 0,
                    "ui": 1,
                    "ui_on_text": "Category",
                    "ui_off_text": "Page"
                },
                {
                    "key": "field_5c3c02e17316d",
                    "label": "Use Custom URL",
                    "name": "use_custom_url",
                    "type": "true_false",
                    "instructions": "Check to use a copy\/paste custom URL. Will overwrite Link Type if this option is set.",
                    "required": 0,
                    "conditional_logic": 0,
                    "wrapper": {
                        "width": "50",
                        "class": "",
                        "id": ""
                    },
                    "message": "",
                    "default_value": 0,
                    "ui": 1,
                    "ui_on_text": "",
                    "ui_off_text": ""
                }
            ]
        }
    ],
    "location": [
        [
            {
                "param": "post_type",
                "operator": "==",
                "value": "custom-nav-menu"
            }
        ]
    ],
    "menu_order": 0,
    "position": "normal",
    "style": "seamless",
    "label_placement": "top",
    "instruction_placement": "label",
    "hide_on_screen": "",
    "active": 1,
    "description": "",
    "modified": 1579631731
}